{
  "name": "Notion",
  "description": "Create, read, and manage pages and databases in Notion workspaces",
  "metadata": {
    "categories": "SaaS & API Integrations,Databases,Verified"
  },
  "icon": "https://avatars.githubusercontent.com/u/4792552?v=4",
  "repoURL": "https://github.com/makenotion/notion-mcp-server",
  "env": [
    {
      "key": "OPENAPI_MCP_HEADERS",
      "name": "OpenAPI MCP Headers",
      "required": true,
      "sensitive": true,
      "description": "JSON-encoded HTTP headers for MCP requests, e.g., {\"Authorization\": \"Bearer ntn_****\", \"Notion-Version\": \"2022-06-28\"}. The Notion Integration token (ntn_****) is required."
    }
  ],
  "args": [
    "-y",
    "@notionhq/notion-mcp-server"
  ],
  "command": "npx"
}